{"cameraMode":{"drawMode":0,"name":"Shaded","section":"Shading Mode"},"sceneLighting":true,"audioPlay":false,"sceneViewState":{"showFog":true,"showMaterialUpdate":false,"showSkybox":true,"showFlares":true,"showImageEffects":true,"showParticleSystems":true},"in2DMode":false,"pivot":{"x":9.556838989257813,"y":12.635208129882813,"z":25.74144172668457},"rotation":{"x":0.6378604173660278,"y":-0.011554531753063202,"z":0.009572012349963189,"w":0.770006537437439},"size":29.339143753051759,"orthographic":false}